Metadata-Version: 2.4
Name: PGAPy
Version: 2.9
Summary: Python wrapper for pgapack, the parallel genetic algorithm library
Home-page: https://github.com/schlatterbeck/pgapy
Author: Ralf Schlatterbeck
Author-email: Ralf Schlatterbeck <rsc@runtux.com>
License-Expression: BSD-2-Clause
Project-URL: Homepage, https://github.com/schlatterbeck/pgapy
Project-URL: Bug Tracker, https://github.com/schlatterbeck/pgapy/issues
Classifier: Development Status :: 5 - Production/Stable
Classifier: Intended Audience :: Developers
Classifier: Intended Audience :: Education
Classifier: Intended Audience :: Science/Research
Classifier: Operating System :: OS Independent
Classifier: Programming Language :: C
Classifier: Programming Language :: Python
Classifier: Topic :: Education
Classifier: Topic :: Scientific/Engineering
Classifier: Topic :: Scientific/Engineering :: Artificial Intelligence
Classifier: Topic :: Software Development :: Libraries
Classifier: Topic :: Software Development :: Libraries :: Python Modules
Requires-Python: >=3.7
License-File: LICENSE
Dynamic: author
Dynamic: home-page
Dynamic: license-file
